{
  "type": "Feature",
  "stac_version": "1.0.0",
  "id": "OR_GLM-L2-LCFA_G16_s20203662359400_e20210010000004_c20210010000030",
  "properties": {
    "start_datetime": "2020-12-31T23:59:40.0Z",
    "end_datetime": "2021-01-01T00:00:00.4Z",
    "mission": "GOES",
    "constellation": "GOES",
    "platform": "GOES-16",
    "instruments": [
      "FM1"
    ],
    "gsd": 8000,
    "processing:level": "L2",
    "processing:facility": "WCDAS",
    "goes:orbital-slot": "East",
    "goes:system-environment": "OR",
    "goes:image-type": "FULL DISK",
    "proj:epsg": 4326,
    "datetime": "2020-12-31T23:59:50.200000Z"
  },
  "geometry": {
    "type": "Polygon",
    "coordinates": [
      [
        [
          -141.56,
          66.56
        ],
        [
          -8.44,
          66.56
        ],
        [
          -8.44,
          -66.56
        ],
        [
          -141.56,
          -66.56
        ],
        [
          -141.56,
          66.56
        ]
      ]
    ]
  },
  "links": [
    {
      "rel": "collection",
      "href": "./collection.json",
      "type": "application/json",
      "title": "GLM L2 Lightning Detections: Events, Groups, and Flashes"
    }
  ],
  "assets": {
    "geoparquet_events": {
      "href": "events.parquet",
      "type": "application/x-parquet",
      "title": "Processed GeoParquet file for events",
      "table:primary_geometry": "geometry",
      "table:columns": [
        {
          "name": "geometry"
        },
        {
          "name": "id",
          "type": "int32",
          "description": "product-unique lightning event identifier"
        },
        {
          "name": "time_offset",
          "type": "int16",
          "description": "GLM L2+ Lightning Detection: event's time of occurrence"
        },
        {
          "name": "energy",
          "type": "int16",
          "description": "GLM L2+ Lightning Detection: event radiant energy"
        },
        {
          "name": "parent_group_id",
          "type": "int32",
          "description": "product-unique lightning group identifier for one or more events"
        }
      ],
      "table:row_count": 11236,
      "roles": [
        "data",
        "cloud-optimized"
      ]
    },
    "geoparquet_flashes": {
      "href": "flashes.parquet",
      "type": "application/x-parquet",
      "title": "Processed GeoParquet file for flashes",
      "table:primary_geometry": "geometry",
      "table:columns": [
        {
          "name": "geometry"
        },
        {
          "name": "id",
          "type": "int16",
          "description": "product-unique lightning flash identifier"
        },
        {
          "name": "time_offset_of_first_event",
          "type": "int16",
          "description": "GLM L2+ Lightning Detection: time of occurrence of first constituent event in flash"
        },
        {
          "name": "time_offset_of_last_event",
          "type": "int16",
          "description": "GLM L2+ Lightning Detection: time of occurrence of last constituent event in flash"
        },
        {
          "name": "frame_time_offset_of_first_event",
          "type": "int16",
          "description": "GLM L2+ Lightning Detection: time of occurrence of first constituent event in flash"
        },
        {
          "name": "frame_time_offset_of_last_event",
          "type": "int16",
          "description": "GLM L2+ Lightning Detection: time of occurrence of last constituent event in flash"
        },
        {
          "name": "area",
          "type": "int16",
          "description": "GLM L2+ Lightning Detection: flash area coverage (pixels containing at least one constituent event only)"
        },
        {
          "name": "energy",
          "type": "int16",
          "description": "GLM L2+ Lightning Detection: flash radiant energy"
        },
        {
          "name": "quality_flag",
          "type": "int16",
          "description": "GLM L2+ Lightning Detection: flash data quality flags"
        }
      ],
      "table:row_count": 179,
      "roles": [
        "data",
        "cloud-optimized"
      ]
    },
    "geoparquet_groups": {
      "href": "groups.parquet",
      "type": "application/x-parquet",
      "title": "Processed GeoParquet file for groups",
      "table:primary_geometry": "geometry",
      "table:columns": [
        {
          "name": "geometry"
        },
        {
          "name": "id",
          "type": "int32",
          "description": "product-unique lightning group identifier"
        },
        {
          "name": "time_offset",
          "type": "int16",
          "description": "GLM L2+ Lightning Detection: mean time of group's constituent events' times of occurrence"
        },
        {
          "name": "frame_time_offset",
          "type": "int16",
          "description": "GLM L2+ Lightning Detection: mean time of group's constituent events' times of occurrence"
        },
        {
          "name": "area",
          "type": "int16",
          "description": "GLM L2+ Lightning Detection: group area coverage (pixels containing at least one constituent event only)"
        },
        {
          "name": "energy",
          "type": "int16",
          "description": "GLM L2+ Lightning Detection: group radiant energy"
        },
        {
          "name": "quality_flag",
          "type": "int16",
          "description": "GLM L2+ Lightning Detection: group data quality flags"
        },
        {
          "name": "parent_flash_id",
          "type": "int16",
          "description": "product-unique lightning flash identifier for one or more groups"
        }
      ],
      "table:row_count": 3706,
      "roles": [
        "data",
        "cloud-optimized"
      ]
    },
    "netcdf": {
      "href": "OR_GLM-L2-LCFA_G16_s20203662359400_e20210010000004_c20210010000030.nc",
      "type": "application/netcdf",
      "title": "Original netCDF 4 file",
      "created": "2021-01-01T00:00:03.0Z",
      "roles": [
        "data",
        "source"
      ]
    }
  },
  "bbox": [
    -141.56,
    -66.56,
    -8.44,
    66.56
  ],
  "stac_extensions": [
    "https://stac-extensions.github.io/goes/v1.0.0/schema.json",
    "https://stac-extensions.github.io/processing/v1.1.0/schema.json",
    "https://stac-extensions.github.io/projection/v1.0.0/schema.json",
    "https://stac-extensions.github.io/table/v1.2.0/schema.json"
  ],
  "collection": "goes-glm"
}